pynxtools_apm/__init__.py
pynxtools_apm/mkdocs.py
pynxtools_apm/reader.py
pynxtools_apm/concepts/__init__.py
pynxtools_apm/concepts/mapping_functors_pint.py
pynxtools_apm/configurations/cameca_cfg.py
pynxtools_apm/configurations/oasis_eln_cfg.py
pynxtools_apm/configurations/oasis_eln_config_cfg.py
pynxtools_apm/examples/usa_madison_cameca_eln.py
pynxtools_apm/nomad/entrypoints.py
pynxtools_apm/nomad/examples/README.md
pynxtools_apm/nomad/examples/apm.archive.json
pynxtools_apm/nomad/examples/apm.oasis.specific.yaml
pynxtools_apm/nomad/examples/downloads.archive.yaml
pynxtools_apm/nomad/examples/nxapm.schema.archive.yaml
pynxtools_apm/nomad/examples/output.nxs_eln_data.yaml
pynxtools_apm/parsers/hfive_base.py
pynxtools_apm/parsers/ifes_ranging.py
pynxtools_apm/parsers/ifes_reconstruction.py
pynxtools_apm/parsers/oasis_config.py
pynxtools_apm/parsers/oasis_eln.py
pynxtools_apm/utils/__init__.py
pynxtools_apm/utils/create_nx_default_plots.py
pynxtools_apm/utils/custom_logging.py
pynxtools_apm/utils/generate_synthetic_data.py
pynxtools_apm/utils/get_checksum.py
pynxtools_apm/utils/get_gitrepo_commit.py
pynxtools_apm/utils/hfive_concepts.py
pynxtools_apm/utils/interpret_boolean.py
pynxtools_apm/utils/io_case_logic.py
pynxtools_apm/utils/parse_composition_table.py
pynxtools_apm/utils/pint_custom_unit_registry.py
pynxtools_apm/utils/remove_uninstantiated.py
pynxtools_apm/utils/string_conversions.py
pynxtools_apm/utils/versioning.py
pynxtools_apm-0.4.2.dist-info/licenses/LICENSE
pynxtools_apm-0.4.2.dist-info/METADATA
pynxtools_apm-0.4.2.dist-info/WHEEL
pynxtools_apm-0.4.2.dist-info/entry_points.txt
pynxtools_apm-0.4.2.dist-info/top_level.txt
pynxtools_apm-0.4.2.dist-info/RECORD
